domain_count_spider
