Metadata-Version: 1.0
Name: domain-count-spider
Version: 0.0.3
Summary: Scrapy spider 
Home-page: https://github.com/ricbartm/domain-count-spider
Author: Ricardo Bartolome
Author-email: UNKNOWN
License: UNKNOWN
Platform: UNKNOWN
